certbot_dns_dnspod_109/__init__.py
certbot_dns_dnspod_109/_internal/__init__.py
certbot_dns_dnspod_109/_internal/dns_dnspod.py
certbot_dns_dnspod_109/_internal/tests/__init__.py
certbot_dns_dnspod_109/_internal/tests/dns_dnspod_test.py
certbot_dns_dnspod_109-1.0.2.dist-info/LICENSE.txt
certbot_dns_dnspod_109-1.0.2.dist-info/METADATA
certbot_dns_dnspod_109-1.0.2.dist-info/WHEEL
certbot_dns_dnspod_109-1.0.2.dist-info/entry_points.txt
certbot_dns_dnspod_109-1.0.2.dist-info/top_level.txt
certbot_dns_dnspod_109-1.0.2.dist-info/RECORD
