Metadata-Version: 2.1
Name: certbot-dns-dnspod-109
Version: 1.0.2
Summary: Dnspod DNS Authenticator plugin for Certbot
Home-page: https://github.com/10935336/certbot-dns-dnspod-109
Author: 10935336
Author-email: 109@pha.pub
License: Apache License 2.0
Project-URL: Homepage, https://github.com/10935336/certbot-dns-dnspod-109
Project-URL: Issues, https://github.com/10935336/certbot-dns-dnspod-109/issues
Classifier: Development Status :: 5 - Production/Stable
Classifier: Environment :: Plugins
Classifier: Intended Audience :: System Administrators
Classifier: License :: OSI Approved :: Apache Software License
Classifier: Operating System :: POSIX :: Linux
Classifier: Programming Language :: Python
Classifier: Programming Language :: Python :: 3
Classifier: Programming Language :: Python :: 3.9
Classifier: Programming Language :: Python :: 3.10
Classifier: Programming Language :: Python :: 3.11
Classifier: Programming Language :: Python :: 3.12
Classifier: Topic :: Internet :: WWW/HTTP
Classifier: Topic :: Security
Classifier: Topic :: System :: Installation/Setup
Classifier: Topic :: System :: Networking
Classifier: Topic :: System :: Systems Administration
Classifier: Topic :: Utilities
Requires-Python: >=3.9
License-File: LICENSE.txt
Requires-Dist: acme>=3.0.1
Requires-Dist: certbot>=3.0.1
Requires-Dist: tencentcloud-sdk-python-common>=3.0.1227
Requires-Dist: tencentcloud-sdk-python-dnspod>=3.0.1227
Provides-Extra: docs
Provides-Extra: test
Requires-Dist: pytest; extra == "test"
